vca_cli/__init__.py
vca_cli/cmd_proc.py
vca_cli/print_utils.py
vca_cli/vca_cli.py
vca_cli/vca_cli_blueprint.py
vca_cli/vca_cli_cluster.py
vca_cli/vca_cli_compute.py
vca_cli/vca_cli_example.py
vca_cli/vca_cli_network.py
vca_cli/vca_cli_utils.py
vca_cli/vca_cli_vca.py
vca_cli-18.0.2.dev30.dist-info/DESCRIPTION.rst
vca_cli-18.0.2.dev30.dist-info/METADATA
vca_cli-18.0.2.dev30.dist-info/RECORD
vca_cli-18.0.2.dev30.dist-info/WHEEL
vca_cli-18.0.2.dev30.dist-info/entry_points.txt
vca_cli-18.0.2.dev30.dist-info/metadata.json
vca_cli-18.0.2.dev30.dist-info/pbr.json
vca_cli-18.0.2.dev30.dist-info/top_level.txt
vcd_cli/__init__.py
vcd_cli/amqp.py
vcd_cli/cluster.py
vcd_cli/extension.py
vcd_cli/login.py
vcd_cli/org.py
vcd_cli/profile.py
vcd_cli/profiles.py
vcd_cli/search.py
vcd_cli/system.py
vcd_cli/task.py
vcd_cli/utils.py
vcd_cli/vapp.py
vcd_cli/vcd.py
vcd_cli/vdc.py
