Metadata-Version: 2.0
Name: vca-cli
Version: 18.0.2.dev30
Summary: VMware vCloud CLI
Home-page: https://github.com/vmware/vca-cli
Author: Paco Gomez
Author-email: pgomez@vmware.com
License: UNKNOWN
Platform: UNKNOWN
Classifier: Environment :: Console
Classifier: Intended Audience :: System Administrators
Classifier: Intended Audience :: Developers
Classifier: Operating System :: POSIX :: Linux
Classifier: Operating System :: MacOS :: MacOS X
Classifier: Operating System :: Microsoft :: Windows
Classifier: Programming Language :: Python
Classifier: Programming Language :: Python :: 2
Classifier: Programming Language :: Python :: 2.7
Classifier: Programming Language :: Python :: 3
Requires-Dist: PrettyTable (>=0.7,<0.8)
Requires-Dist: PyYAML (>=3.10)
Requires-Dist: Pygments
Requires-Dist: click (>=6.7)
Requires-Dist: colorama (>=0.3.3)
Requires-Dist: cryptography (>=0.9.1)
Requires-Dist: oslo.utils
Requires-Dist: python-dateutil (>=2.4.2)
Requires-Dist: pytz
Requires-Dist: pyvcloud (>=18.0.4.dev28)
Requires-Dist: requests (>=2.4.3)
Requires-Dist: six
Requires-Dist: tabulate (>=0.7.5)
Requires-Dist: xmltodict (>=0.9.2)
